mergeconfigs/__init__.py
mergeconfigs/__main__.py
mergeconfigs/cli.py
mergeconfigs/config_builder.py
mergeconfigs-0.10.dist-info/LICENSE.txt
mergeconfigs-0.10.dist-info/METADATA
mergeconfigs-0.10.dist-info/WHEEL
mergeconfigs-0.10.dist-info/top_level.txt
mergeconfigs-0.10.dist-info/RECORD
