Metadata-Version: 2.1
Name: mergeconfigs
Version: 0.10
Summary: Help developers with config files
Home-page: https://github.com/x41lakazam/mergeconfigs
Author: Eyal Chocron
Author-email: x41lakazam@gmail.com
Maintainer: Eyal Chocron
Maintainer-email: x41lakazam@gmail.com
Keywords: config,yaml,inheritance,templates
Requires-Python: >=3.7
License-File: LICENSE.txt
Requires-Dist: click
Requires-Dist: pyyaml (>=5.1)
